{
  "_fv": 33,
  "_type": "achievement",
  "definition": {
    "achievementName": "The Easy Way Out!",
    "achievementDescription": "Hey! It's ok to need help. It's not like you weren't supposed to do that!",
    "achievementIcon": {
      "value": "CUSTOM:AstralTome"
    },
    "background": "Default",
    "disableDisplay": false,
    "showPopup": true,
    "announceToChat": true,
    "hideIfNotCompleted": false,
    "rewardLoot": [],
    "rewardRecipes": [],
    "rewardFunction": "No function",
    "rewardXP": 0,
    "achievementType": "goal",
    "parent": {
      "value": "CUSTOM:FractalFromSeeds"
    },
    "triggerxml": "<xml xmlns=\"https://developers.google.com/blockly/xml\"><block type=\"item_in_inventory\" x=\"49\" y=\"23\"><value name=\"amount_l\"><block type=\"math_number\"><field name=\"NUM\">1</field></block></value><value name=\"amount_h\"><block type=\"math_number\"><field name=\"NUM\">1</field></block></value><value name=\"item\"><block type=\"mcitem_all\"><field name=\"value\">CUSTOM:AstralTome</field></block></value><next><block type=\"advancement_trigger\" deletable=\"false\"></block></next></block></xml>"
  }
}