{
  "format_version": "1.15.0",
  "minecraft:biome": {
    "description": {
      "identifier": "cherry_blossom_grove"
    },
    "components": {
      "minecraft:climate": {
        "downfall": 0.7,
        "snow_accumulation": [ 0.0, 0.125 ],
        "temperature": 0.5
      },
      "minecraft:overworld_height": {
         "noise_params": [ -0.1, 0.1 ]
      },
      "minecraft:surface_parameters": {
        "sea_floor_depth": 7,
        "sea_floor_material": "minecraft:gravel",
        "foundation_material": "minecraft:stone",
        "mid_material": "minecraft:dirt",
        "top_material": "minecraft:grass",
        "sea_material": "minecraft:water"
      },

     //////////////////////////////////////////////////////////////////////////////

      "cherry_blossom_grove": {},
      "overworld": {},

      // Climate
      "medium": {},

      // Entities
      "monster": {},
      "butterfly": {},

      // Vegetation
      "bush_oak": {},
      "grass_normal": {},
      "waterlily": {},
      "oak_sapling": {},
      "cherry_blossom_tree": {},

      // Underground
      "default_ores": {},

     //////////////////////////////////////////////////////////////////////////////

      "minecraft:overworld_generation_rules": {
        "generate_for_climates": [
          [ "medium", 1 ]
        ]
      }
    }
  }
}
